rocca/__init__.py
rocca/association_rule/__init__.py
rocca/association_rule/_apriori.py
rocca/clustering/__init__.py
rocca/clustering/_k_means.py
rocca/ensemble/__init__.py
rocca/ensemble/_bagging.py
rocca/ensemble/_random_forest.py
rocca/ensemble/_xgboost.py
rocca/tree/__init__.py
rocca/tree/_decision_tree.py
rocca/tree/_decision_tree_xgb.py
rocca/tree/_regression_tree.py
rocca/utils/__init__.py
rocca/utils/_helpers.py
rocca-0.1.0.dist-info/LICENSE.txt
rocca-0.1.0.dist-info/METADATA
rocca-0.1.0.dist-info/WHEEL
rocca-0.1.0.dist-info/top_level.txt
rocca-0.1.0.dist-info/RECORD
