Metadata-Version: 2.1
Name: rocca
Version: 0.1.0
Summary: Library Machine Learning Python yang simple dan lengkap 
Home-page: https://github.com/JeffriLieca/rocca
Author: Jeffri Lieca H
Author-email: handoyojeffri@gmail.com
Keywords: simple,apriori,tree,cluster,machine learning,code,python
Classifier: Development Status :: 3 - Alpha
Classifier: Intended Audience :: Education
Classifier: License :: OSI Approved :: MIT License
Classifier: Programming Language :: Python :: 3
Classifier: Programming Language :: Python :: 3.8
Classifier: Programming Language :: Python :: 3.9
Classifier: Programming Language :: Python :: 3.10
Classifier: Programming Language :: Python :: 3.11
Classifier: Programming Language :: Python :: 3.12
Classifier: Topic :: Scientific/Engineering :: Artificial Intelligence
Requires-Python: >=3.7
License-File: LICENSE.txt
Requires-Dist: numpy
Requires-Dist: matplotlib
Requires-Dist: pandas
Requires-Dist: scikit-learn
